lnregtest/__init__.py
lnregtest/lnregtest.py
lnregtest/lib/__init__.py
lnregtest/lib/common.py
lnregtest/lib/graph_testing.py
lnregtest/lib/network.py
lnregtest/lib/network_components.py
lnregtest/lib/node_config_templates.py
lnregtest/lib/utils.py
lnregtest/network_definitions/__init__.py
lnregtest/network_definitions/default.py
lnregtest/network_definitions/mutated_default.py
lnregtest/network_definitions/star_ring.py
lnregtest/network_definitions/star_ring_electrum.py
test/__init__.py
test/test_basic.py
test/test_electrum.py
test/test_graphs.py
lnregtest-0.2.2.dist-info/METADATA
lnregtest-0.2.2.dist-info/WHEEL
lnregtest-0.2.2.dist-info/entry_points.txt
lnregtest-0.2.2.dist-info/top_level.txt
lnregtest-0.2.2.dist-info/RECORD
