Metadata-Version: 2.1
Name: lnregtest
Version: 0.2.2
Summary: Bitcoin regtest Lightning Network for integration testing.
Home-page: https://github.com/bitromortac/lnregtest
Author: bitromortac
Author-email: bitromortac@protonmail.com
License: UNKNOWN
Platform: UNKNOWN
Classifier: Programming Language :: Python :: 3
Classifier: License :: OSI Approved :: MIT License
Classifier: Operating System :: OS Independent
Requires-Dist: wheel
